release_version/__init__.py
release_version/config.py
release_version/main.py
release_version/py.typed
release_version/utils.py
release_version-0.1.6.dist-info/LICENSE
release_version-0.1.6.dist-info/METADATA
release_version-0.1.6.dist-info/WHEEL
release_version-0.1.6.dist-info/entry_points.txt
release_version-0.1.6.dist-info/top_level.txt
release_version-0.1.6.dist-info/RECORD
