Metadata-Version: 2.1
Name: release-version
Version: 0.1.6
Summary: Yet another tool for bumping version number and updating changelog
Author-email: Tuomas Siipola <tuomas.siipola@fmi.fi>
License: MIT License
Project-URL: Homepage, https://github.com/actris-cloudnet/release-version
Project-URL: Bug Reports, https://github.com/actris-cloudnet/release-version/issues
Project-URL: Source, https://github.com/actris-cloudnet/release-version/
Keywords: development
Classifier: Development Status :: 3 - Alpha
Classifier: Intended Audience :: Developers
Classifier: License :: OSI Approved :: MIT License
Classifier: Programming Language :: Python :: 3.10
Classifier: Programming Language :: Python :: 3.11
Classifier: Programming Language :: Python :: 3.12
Classifier: Programming Language :: Python :: 3.8
Classifier: Programming Language :: Python :: 3.9
Classifier: Topic :: Software Development
Requires-Python: >=3.8
License-File: LICENSE
Requires-Dist: tomli >=2.0.1
Provides-Extra: dev
Requires-Dist: mypy ; extra == 'dev'
Requires-Dist: pre-commit ; extra == 'dev'
Requires-Dist: pytest ; extra == 'dev'
Requires-Dist: types-toml ; extra == 'dev'
